yamlsub/__init__.py
yamlsub/config.py
yamlsub-1.3.8.dist-info/LICENSE
yamlsub-1.3.8.dist-info/METADATA
yamlsub-1.3.8.dist-info/WHEEL
yamlsub-1.3.8.dist-info/top_level.txt
yamlsub-1.3.8.dist-info/RECORD
